[
  {
    "id": 1,
    "day": "12",
    "month": "APR",
    "year": "бҹўбҹ бҹўбҹҰ",
    "title": "Navathon: бһҠбҹҶбһҺбҹ„бҹҮбһҹбҹ’бһҡбһ¶бһҷбһ‘бһ№бһҖбһҹбҹ’бһўбһ¶бһҸ",
    "type": "Navathon",
    "typeColor": "text-[#CC0000] bg-red-50",
    "location": "бһ—бҹ’бһ“бҹҶбһ–бҹҒбһү + бһўбһ“бһЎбһ¶бһү",
    "spots": "бһ“бҹ…бһҹбһӣбҹӢ 48 бһҖбҹ…бһўбһё",
    "spotsUrgent": true,
    "image": "https://images.unsplash.com/photo-1520975682031-a4a9c7aef2d5?auto=format&fit=crop&w=1200&q=80"
  },
  {
    "id": 2,
    "day": "21",
    "month": "APR",
    "year": "бҹўбҹ бҹўбҹҰ",
    "title": "бһ”бһҺбҹ’бһҸбһ»бҹҮбһ”бһҺбҹ’бһҸбһ¶бһӣбһҹбһҳбҹ’бһҡбһ¶бһ”бҹӢбһҖбһ¶бһҡбһҶбҹ’бһӣбһҫбһҷбһҸбһ”бһҳбһ“бһ»бһҹбҹ’бһҹбһ’бһҳбҹҢ",
    "type": "Training",
    "typeColor": "text-[#CC0000] bg-red-50",
    "location": "бһ—бҹ’бһ“бҹҶбһ–бҹҒбһү, бһҖбһҳбҹ’бһ–бһ»бһҮбһ¶",
    "spots": "бһ“бҹ…бһҹбһӣбҹӢ 12 бһҖбҹ…бһўбһё",
    "spotsUrgent": true,
    "image": "https://images.unsplash.com/photo-1521737604893-d14cc237f11d?auto=format&fit=crop&w=1200&q=80"
  },
  {
    "id": 3,
    "day": "05",
    "month": "APR",
    "year": "бҹўбҹ бҹўбҹҰ",
    "title": "Design Thinking бһҹбһҳбҹ’бһҡбһ¶бһ”бҹӢбһ•бһӣбһ”бҹ’бһҡбһҷбҹ„бһҮбһ“бҹҚбһҹбһ„бҹ’бһӮбһҳ",
    "type": "Workshop",
    "typeColor": "text-[#CC0000] bg-red-50",
    "location": "бһҖбҹҶбһ–бһ„бҹӢбһ…бһ¶бһҳ, бһҖбһҳбҹ’бһ–бһ»бһҮбһ¶",
    "spots": "бһ…бһјбһӣбһҡбһҪбһҳбһ”бһ¶бһ“",
    "spotsUrgent": false,
    "image": "https://images.unsplash.com/photo-1519389950473-47ba0277781c?auto=format&fit=crop&w=1200&q=80"
  },
  {
    "id": 4,
    "day": "02",
    "month": "MAY",
    "year": "бҹўбҹ бҹўЫ¶",
    "title": "Navathon: Hack бһ‘бҹ…бһӣбһҫбһҖбһ¶бһҡбһ‘бһ‘бһҪбһӣбһ”бһ¶бһ“бһҖбһ¶бһҡбһўбһ”бҹӢбһҡбҹҶ",
    "type": "Navathon",
    "typeColor": "text-[#CC0000] bg-red-50",
    "location": "бһҹбҹҖбһҳбһҡбһ¶бһ”, бһҖбһҳбҹ’бһ–бһ»бһҮбһ¶",
    "spots": "бһ“бҹ…бһҹбһӣбҹӢ 30 бһҖбҹ…бһўбһё",
    "spotsUrgent": false,
    "image": "https://images.unsplash.com/photo-1522071820081-009f0129c71c?auto=format&fit=crop&w=1200&q=80"
  },
  {
    "id": 5,
    "day": "10",
    "month": "MAY",
    "year": "бҹўбҹ бҹўбҹҰ",
    "title": "Navathon: бһ”бһ…бҹ’бһ…бҹҒбһҖбһңбһ·бһ‘бҹ’бһҷбһ¶бһҹбһҳбҹ’бһҡбһ¶бһ”бҹӢбһҹбһ»бһңбһҸбҹ’бһҗбһ·бһ—бһ¶бһ–бһҖбһ»бһҳбһ¶бһҡ",
    "type": "Navathon",
    "typeColor": "text-[#CC0000] bg-red-50",
    "location": "бһ”бһ“бҹ’бһ‘бһ¶бһҷбһҳбһ¶бһ“бһҮбҹҗбһҷ, бһҖбһҳбҹ’бһ–бһ»бһҮбһ¶",
    "spots": "бһ”бһҫбһҖбһҖбһ¶бһҡбһ…бһ»бҹҮбһҲбҹ’бһҳбҹ„бҹҮ",
    "spotsUrgent": false,
    "image": "https://images.unsplash.com/photo-1521737711867-e3b97375f902?auto=format&fit=crop&w=1200&q=80"
  }
]
